textcompose/__init__.py
textcompose/template.py
textcompose/containers/__init__.py
textcompose/containers/base.py
textcompose/containers/group.py
textcompose/containers/list.py
textcompose/core/__init__.py
textcompose/core/component.py
textcompose/core/resolvers.py
textcompose/core/types.py
textcompose/elements/__init__.py
textcompose/elements/base.py
textcompose/elements/format.py
textcompose/elements/jinja.py
textcompose/elements/progress_bar.py
textcompose/elements/text.py
textcompose/logics/__init__.py
textcompose/logics/base.py
textcompose/logics/if_then_else.py
textcompose/styles/__init__.py
textcompose/styles/progress_bar.py
textcompose-1.3.0.dist-info/METADATA
textcompose-1.3.0.dist-info/WHEEL
textcompose-1.3.0.dist-info/licenses/LICENSE
textcompose-1.3.0.dist-info/RECORD
