Metadata-Version: 2.4
Name: textcompose
Version: 1.3.0
Summary: A Python library for building dynamic, structured text templates using a declarative, compose-based approach
Project-URL: Homepage, https://github.com/m-xim/textcompose
Project-URL: Repository, https://github.com/m-xim/textcompose
Project-URL: Issues, https://github.com/m-xim/textcompose/issues
Author-email: m-xim <i@m-xim.ru>
License: Apache-2.0
License-File: LICENSE
Keywords: compose,logic templates,structured text,template,templating,text generation
Classifier: License :: OSI Approved :: Apache Software License
Classifier: Operating System :: OS Independent
Classifier: Programming Language :: Python :: 3
Classifier: Programming Language :: Python :: 3.10
Classifier: Programming Language :: Python :: 3.11
Classifier: Programming Language :: Python :: 3.12
Classifier: Programming Language :: Python :: 3.13
Classifier: Topic :: Software Development :: Libraries
Classifier: Topic :: Text Processing :: General
Requires-Python: >=3.10
Requires-Dist: jinja2>=3.1.6
Requires-Dist: magic-filter>=1.0.12
Requires-Dist: python-box>=7.3.2
